qcs_data/__init__.py
qcs_data/downloader.py
qcs_data/filter.py
qcs_data-0.1.1.dist-info/METADATA
qcs_data-0.1.1.dist-info/WHEEL
qcs_data-0.1.1.dist-info/top_level.txt
qcs_data-0.1.1.dist-info/RECORD
