Metadata-Version: 2.1
Name: qcs_data
Version: 0.1.1
Author: TUM QCS
Classifier: Programming Language :: Python :: 3
Requires-Dist: requests
